{ "frames": {
   "level_one.png": {
    "frame": { "x": 0, "y": 0, "w": 800, "h": 600 },
    "rotated": false,
    "trimmed": false,
    "spriteSourceSize": { "x": 0, "y": 0, "w": 800, "h": 600 },
    "sourceSize": { "w": 800, "h": 600 },
    "duration": 100
   }
 },
 "meta": {
  "app": "http://www.aseprite.org/",
  "version": "1.1.13",
  "image": "/Users/vincentcastelli/Documents/01_HackReactor/HR95Repos/MVP/hrsf95-mvp/html5/assets/level_one-sheet.png",
  "format": "RGBA8888",
  "size": { "w": 800, "h": 600 },
  "scale": "1",
  "frameTags": [
  ],
  "layers": [
   { "name": "Layer 1", "opacity": 255, "blendMode": "normal" }
  ]
 }
}
